Verilog Procesador/ALU.v
module ALU (
    input  wire [31:0] a,
    input  wire [31:0] b,
    input  wire [3:0]  instruccion,
    output reg  [31:0] salida,
    output wire [31:0] multiplicacion_high_part
);
        wire [63:0] mul_u;
        wire signed [31:0] a_s;
        wire signed [31:0] b_s;
        wire signed [63:0] mul_ss;

        assign mul_u = a * b;
        assign a_s = a;
        assign b_s = b;
        assign mul_ss = a_s * b_s;

        // Parte alta de multiplicación con signo (estilo MULH)
        assign multiplicacion_high_part = mul_ss[63:32];

        always @(*) begin
            case (instruccion)
                4'h0: salida = a + b;                    // ADD
                4'h1: salida = a - b;                    // SUB
                4'h2: salida = mul_u[31:0];              // MUL (parte baja)
                4'h3: salida = (b != 0) ? (a / b) : 0;   // DIV
                4'h4: salida = a & b;                    // AND
                4'h5: salida = a | b;                    // OR
                4'h6: salida = a ^ b;                    // XOR
                4'h7: salida = ~a;                       // NOT
                4'h8: salida = a << b[4:0];              // SHL
                4'h9: salida = a >> b[4:0];              // SHR
                4'hA: salida = mul_ss[63:32];            // MULH (parte alta signed*signed)
                4'hB: salida = mul_u[63:32];             // MULHU (parte alta unsigned*unsigned)
                default: salida = 32'b0;                 // NOP
            endcase
        end
endmodule

Verilog Procesador/tb_ALU.v
`timescale 1ns/1ps

module tb_ALU;
    reg  [31:0] a;
    reg  [31:0] b;
    reg  [3:0]  instruccion;
    wire [31:0] salida;
    wire [31:0] multiplicacion_high_part;

    ALU dut (
        .a(a),
        .b(b),
        .instruccion(instruccion),
        .salida(salida),
        .multiplicacion_high_part(multiplicacion_high_part)
    );

    initial begin
        $dumpfile("ALU_test.vcd");
        $dumpvars(0, tb_ALU);

        // ADD
        a = 32'd10; b = 32'd5; instruccion = 4'h0; #10;
        // SUB
        a = 32'd10; b = 32'd7; instruccion = 4'h1; #10;
        // MUL (low 32)
        a = 32'h0001_0002; b = 32'h0000_0003; instruccion = 4'h2; #10;
        // MULH signed*signed (high 32)
        a = 32'hFFFF_FFFE; b = 32'h0000_0004; instruccion = 4'hA; #10;
        // MULHU unsigned*unsigned (high 32)
        a = 32'hFFFF_FFFE; b = 32'h0000_0004; instruccion = 4'hB; #10;
        // DIV
        a = 32'd100; b = 32'd10; instruccion = 4'h3; #10;
        // AND
        a = 32'hF0F0_F0F0; b = 32'h0FF0_0FF0; instruccion = 4'h4; #10;
        // OR
        a = 32'hF0F0_0000; b = 32'h0FF0_000F; instruccion = 4'h5; #10;
        // XOR
        a = 32'hAAAA_AAAA; b = 32'h5555_5555; instruccion = 4'h6; #10;
        // SHL
        a = 32'h0000_0001; b = 32'd4; instruccion = 4'h8; #10;
        // SHR
        a = 32'h8000_0000; b = 32'd4; instruccion = 4'h9; #10;

        $finish;
    end
endmodule

Verilog Procesador/ALU_test.vcd
$date
	Wed Mar 18 19:24:28 2026
$end
$version
	Icarus Verilog
$end
$timescale
	1ps
$end
$scope module tb_ALU $end
$var wire 32 ! salida [31:0] $end
$var wire 32 " multiplicacion_high_part [31:0] $end
$var reg 32 # a [31:0] $end
$var reg 32 $ b [31:0] $end
$var reg 4 % instruccion [3:0] $end
$scope module dut $end
$var wire 32 & a [31:0] $end
$var wire 32 ' a_s [31:0] $end
$var wire 32 ( b [31:0] $end
$var wire 32 ) b_s [31:0] $end
$var wire 4 * instruccion [3:0] $end
$var wire 32 + multiplicacion_high_part [31:0] $end
$var wire 64 , mul_u [63:0] $end
$var wire 64 - mul_ss [63:0] $end
$var reg 32 . salida [31:0] $end
$upscope $end
$upscope $end
$enddefinitions $end
$comment Show the parameter values. $end
$dumpall
$end
#0
$dumpvars
b1111 .
b110010 -
b110010 ,
b0 +
b0 *
b101 )
b101 (
b1010 '
b1010 &
b0 %
b101 $
b1010 #
b0 "
b1111 !
$end
#10000
b11 !
b11 .
b1 %
b1 *
b1000110 -
b111 )
b1000110 ,
b111 $
b111 (
#20000
b110000000000000110 !
b110000000000000110 .
b10 %
b10 *
b11 )
b11 $
b11 (
b110000000000000110 -
b10000000000000010 '
b110000000000000110 ,
b10000000000000010 #
b10000000000000010 &
#30000
b11111111111111111111111111111111 "
b11111111111111111111111111111111 +
b11111111111111111111111111111111 !
b11111111111111111111111111111111 .
b1010 %
b1010 *
b100 )
b100 $
b100 (
b1111111111111111111111111111111111111111111111111111111111111000 -
b11111111111111111111111111111110 '
b1111111111111111111111111111111000 ,
b11111111111111111111111111111110 #
b11111111111111111111111111111110 &
#40000
b11 !
b11 .
b1011 %
b1011 *
#50000
b0 "
b0 +
b1010 !
b1010 .
b11 %
b11 *
b1010 )
b1010 $
b1010 (
b1111101000 -
b1100100 '
b1111101000 ,
b1100100 #
b1100100 &
#60000
b11111111000011111111111100001111 "
b11111111000011111111111100001111 +
b111100000000000011110000 !
b111100000000000011110000 .
b100 %
b100 *
b1111111100000000111111110000 )
b1111111100000000111111110000 $
b1111111100000000111111110000 (
b1111111100001111111111110000111111110000111111111111000100000000 -
b11110000111100001111000011110000 '
b111100000000000011101111111111110000111111111111000100000000 ,
b11110000111100001111000011110000 #
b11110000111100001111000011110000 &
#70000
b11111111000011111111000011111111 "
b11111111000011111111000011111111 +
b11111111111100000000000000001111 !
b11111111111100000000000000001111 .
b101 %
b101 *
b1111111100000000000000001111 )
b1111111100000000000000001111 $
b1111111100000000000000001111 (
b1111111100001111111100001111111100011110000100000000000000000000 -
b11110000111100000000000000000000 '
b111011111111111100010000111000011110000100000000000000000000 ,
b11110000111100000000000000000000 #
b11110000111100000000000000000000 &
#80000
b11100011100011100011100011100011 "
b11100011100011100011100011100011 +
b11111111111111111111111111111111 !
b11111111111111111111111111111111 .
b110 %
b110 *
b1010101010101010101010101010101 )
b1010101010101010101010101010101 $
b1010101010101010101010101010101 (
b1110001110001110001110001110001101110001110001110001110001110010 -
b10101010101010101010101010101010 '
b11100011100011100011100011100001110001110001110001110001110010 ,
b10101010101010101010101010101010 #
b10101010101010101010101010101010 &
#90000
b0 "
b0 +
b10000 !
b10000 .
b1000 %
b1000 *
b100 )
b100 $
b100 (
b100 -
b1 '
b100 ,
b1 #
b1 &
#100000
b11111111111111111111111111111110 "
b11111111111111111111111111111110 +
b1000000000000000000000000000 !
b1000000000000000000000000000 .
b1001 %
b1001 *
b1111111111111111111111111111111000000000000000000000000000000000 -
b10000000000000000000000000000000 '
b1000000000000000000000000000000000 ,
b10000000000000000000000000000000 #
b10000000000000000000000000000000 &
